.DS_Store
m2mclient/.DS_Store
m2mclient/__init__.py
m2mclient/_version.py
m2mclient/bencode.py
m2mclient/dispatcher.py
m2mclient/packetbase.py
m2mclient/packets.py
m2mclient/wsclient.py
m2mclient-0.0.4.dist-info/DESCRIPTION.rst
m2mclient-0.0.4.dist-info/METADATA
m2mclient-0.0.4.dist-info/RECORD
m2mclient-0.0.4.dist-info/WHEEL
m2mclient-0.0.4.dist-info/metadata.json
m2mclient-0.0.4.dist-info/top_level.txt
