Metadata-Version: 2.0
Name: m2mclient
Version: 0.0.4
Summary: A client for the Dataplicity M2M server
Home-page: https://www.dataplicity.com
Author: WildFoundry
Author-email: support@dataplicity.com
License: UNKNOWN
Platform: any
Classifier: Development Status :: 3 - Alpha
Classifier: Intended Audience :: Developers
Classifier: Programming Language :: Python
Requires-Dist: enum34
Requires-Dist: six
Requires-Dist: websocket-client (==0.37.0)
